LICENSE.txt
MANIFEST.in
README.txt
VERSION.txt
djangout.py
setup.cfg
setup.py
djangout.egg-info/PKG-INFO
djangout.egg-info/SOURCES.txt
djangout.egg-info/dependency_links.txt
djangout.egg-info/entry_points.txt
djangout.egg-info/not-zip-safe
djangout.egg-info/requires.txt
djangout.egg-info/top_level.txt