Metadata-Version: 1.1
Name: djangout
Version: 1.1
Summary: Buildout recipes for Django
Home-page: http://bitbucket.org/2degrees/djangout/
Author: 2degrees Limited
Author-email: 2degrees-dev@googlegroups.com
License: BSD (http://dev.2degreesnetwork.com/p/2degrees-license.html)
Keywords: buildout recipe django media
Platform: UNKNOWN
Classifier: Development Status :: 5 - Production/Stable
Classifier: Environment :: Web Environment
Classifier: Framework :: Buildout
Classifier: Framework :: Django
Classifier: Intended Audience :: Developers
Classifier: License :: OSI Approved :: BSD License
Classifier: Natural Language :: English
Classifier: Operating System :: OS Independent
Classifier: Programming Language :: Python :: 2
Classifier: Topic :: Internet :: WWW/HTTP
